{
  "users": [
    {
      "nome": "Markus KiQ",
      "email": "markus@gmail.com",
      "senha": "undefined",
      "permissoes": "Admin",
      "id": 1
    },
    {
      "id": 2,
      "nome": "Daluncio",
      "email": "daluncio@gmail.com"
    },
    {
      "id": 3,
      "nome": "Murphis",
      "email": "murphis@gmail.com"
    },
    {
      "nome": "Murphys",
      "email": "murphys@gmail.com",
      "id": 5
    },
    {
      "nome": "Murphys Depay",
      "email": "murphys@gmail.com",
      "id": 6
    },
    {
      "nome": "Renato Augusto",
      "email": "renato@sccp.com",
      "senha": "corinthians1234",
      "permissoes": "Colaborador",
      "id": 8
    },
    {
      "nome": "Guerrero",
      "email": "guerrero@sccp.com",
      "senha": "mundial",
      "permissoes": "Admin",
      "id": 9
    },
    {
      "email": "mbppe@rmadrid.com",
      "password": "$2a$10$dzTmZFttP78gBN1ypcqODumbd2Xgr6DH6XgNmjdM9JId0B/SsU9gu",
      "nome": "Mbappe",
      "permissoes": "admin",
      "id": 10
    },
    {
      "email": "r9@email.com",
      "password": "$2a$10$rW.WM04U25Blslg2pVUKiOMfq5AEI2k6V/uoNa7nWyHFKa80qHdtC",
      "nome": "Ronaldo Nazario",
      "permissoes": "Admin",
      "id": 11
    },
    {
      "email": "admin@adm.com",
      "password": "$2a$10$8xWcHP3ZksN0T.nuzDCjxurY7se6TU/pJUgV.TgY6vorgJbXESYhq",
      "nome": "admin",
      "permissoes": "Admin",
      "id": 12
    },
    {
      "email": "colaborador@colab.com",
      "password": "$2a$10$iibJGy4yQpo/cp2CQEsoUu5s9thWHvlUFu0/K34r7tbZYo894ZCVO",
      "nome": "Colaborador",
      "permissoes": "Colaborador",
      "id": 13
    }
  ],
  "clientes": [
    {
      "id": 1,
      "nome": "Cristiano Ronaldo",
      "cpf": "123.456.789-00",
      "dataNascimento": "1985-02-05",
      "email": "cr7@realmadrid.com",
      "telefone": "(11) 91234-5678",
      "logradouro": "Rua das Estrelas",
      "numero": "1000",
      "complemento": "Apto 101",
      "bairro": "Centro",
      "cidade": "Madrid",
      "estado": "ES"
    },
    {
      "nome": "Ronaldo Nazario",
      "cpf": "049.251.460-12",
      "dataNascimento": "1978-04-14",
      "email": "ronaldo@fenomeno.com",
      "telefone": "(11) 99641-2405",
      "logradouro": "Av. Brasil",
      "numero": "5567",
      "complemento": "Apt 201",
      "bairro": "Centro",
      "cidade": "São Paulo",
      "estado": "SP",
      "id": 2
    },
    {
      "nome": "Neymar Jr",
      "cpf": "245.234.636-90",
      "dataNascimento": "1990-09-04",
      "email": "ney@barcelona.com",
      "telefone": "(11) 99790-4367",
      "logradouro": "Rua Barça",
      "numero": "4889",
      "complemento": "Apt 401",
      "bairro": "Centro",
      "cidade": "Santos",
      "estado": "SP",
      "id": 3
    }
  ]
}